LICENSE
README.md
pyproject.toml
setup.cfg
setup.py
src/msdss_models_api/__init__.py
src/msdss_models_api/core.py
src/msdss_models_api/defaults.py
src/msdss_models_api/env.py
src/msdss_models_api/handlers.py
src/msdss_models_api/managers.py
src/msdss_models_api/models.py
src/msdss_models_api/routers.py
src/msdss_models_api/tools.py
src/msdss_models_api.egg-info/PKG-INFO
src/msdss_models_api.egg-info/SOURCES.txt
src/msdss_models_api.egg-info/dependency_links.txt
src/msdss_models_api.egg-info/requires.txt
src/msdss_models_api.egg-info/top_level.txt