Metadata-Version: 2.1
Name: msdss-models-api
Version: 0.0.7
Summary: Model management API for the Modular Spatial Decision Support Systems (MSDSS) framework
Home-page: https://github.com/rrwen/msdss-models-api
Author: Richard Wen
Author-email: rrwen.dev@gmail.com
License: UNKNOWN
Project-URL: Bug Tracker, https://github.com/rrwen/msdss-models-api/issues
Platform: UNKNOWN
Classifier: Programming Language :: Python :: 3
Classifier: License :: OSI Approved :: MIT License
Classifier: Operating System :: OS Independent
Requires-Python: >=3.8
Provides-Extra: users-postgresql
Provides-Extra: users-mysql
Provides-Extra: users-sqlite
Provides-Extra: postgresql
Provides-Extra: mysql
Provides-Extra: sqlite
License-File: LICENSE
